pluralsight/__init__.py
pluralsight/exceptions.py
pluralsight/models/user.py
pluralsight/models/invite.py
pluralsight/models/__init__.py
pluralsight/models/team.py
pluralsight/licensing/invites.py
pluralsight/licensing/users.py
pluralsight/licensing/client.py
pluralsight/licensing/teams.py
pluralsight/licensing/__init__.py
pluralsight/reports/client.py
pluralsight/reports/__init__.py
pluralsight-2.1.2.dist-info/RECORD
pluralsight-2.1.2.dist-info/metadata.json
pluralsight-2.1.2.dist-info/WHEEL
pluralsight-2.1.2.dist-info/DESCRIPTION.rst
pluralsight-2.1.2.dist-info/top_level.txt
pluralsight-2.1.2.dist-info/METADATA
